edfi_schoology_extractor/__init__.py
edfi_schoology_extractor/__main__.py
edfi_schoology_extractor/api/__init__.py
edfi_schoology_extractor/api/paginated_result.py
edfi_schoology_extractor/api/request_client.py
edfi_schoology_extractor/client_facade.py
edfi_schoology_extractor/extract_facade.py
edfi_schoology_extractor/helpers/__init__.py
edfi_schoology_extractor/helpers/arg_parser.py
edfi_schoology_extractor/helpers/constants.py
edfi_schoology_extractor/helpers/csv_reader.py
edfi_schoology_extractor/helpers/csv_writer.py
edfi_schoology_extractor/helpers/sync.py
edfi_schoology_extractor/lms_filesystem.py
edfi_schoology_extractor/mapping/__init__.py
edfi_schoology_extractor/mapping/assignments.py
edfi_schoology_extractor/mapping/attendance.py
edfi_schoology_extractor/mapping/constants.py
edfi_schoology_extractor/mapping/discussion_replies.py
edfi_schoology_extractor/mapping/discussions.py
edfi_schoology_extractor/mapping/section_associations.py
edfi_schoology_extractor/mapping/section_update_comments.py
edfi_schoology_extractor/mapping/section_updates.py
edfi_schoology_extractor/mapping/sections.py
edfi_schoology_extractor/mapping/submissions.py
edfi_schoology_extractor/mapping/usage_analytics.py
edfi_schoology_extractor/mapping/users.py
edfi_schoology_extractor/usage_analytics_facade.py
edfi_schoology_extractor-1.2.2.dist-info/METADATA
edfi_schoology_extractor-1.2.2.dist-info/WHEEL
edfi_schoology_extractor-1.2.2.dist-info/RECORD
