Metadata-Version: 2.1
Name: edfi-schoology-extractor
Version: 1.2.2
Summary: Extract tool for retrieving student data from Canvas
Home-page: https://docs.ed-fi.org/getting-started/edfi-exchange/technology/ed-fi-lms-toolkit
License: Apache-2.0
Author: Ed-Fi Alliance, LLC, and contributors
Requires-Python: >3.9.1,<4.0.0
Classifier: License :: OSI Approved :: Apache Software License
Classifier: Programming Language :: Python :: 3
Classifier: Programming Language :: Python :: 3.10
Classifier: Programming Language :: Python :: 3.11
Classifier: Programming Language :: Python :: 3.12
Requires-Dist: SQLAlchemy (>=1.3.20,<2.0.0)
Requires-Dist: configargparse (>=1.2.3,<2.0.0)
Requires-Dist: cryptography (>=44.0.1,<45.0.0)
Requires-Dist: edfi-lms-extractor-lib (>=1.1.6,<2.0.0)
Requires-Dist: edfi-lms-file-utils (>=1.0.6,<2.0.0)
Requires-Dist: errorhandler (>=2.0.1,<3.0.0)
Requires-Dist: numpy (>=1,<2)
Requires-Dist: oauthlib (>=3.1.0,<4.0.0)
Requires-Dist: opnieuw (>=1.1.0,<2.0.0)
Requires-Dist: pandas (<2.0.0)
Requires-Dist: python-dotenv (==0.15.0)
Requires-Dist: requests (>=2.24.0,<3.0.0)
Requires-Dist: requests_oauthlib (>=1.3.0,<2.0.0)
Project-URL: Repository, https://github.com/Ed-Fi-Exchange-OSS/LMS-Toolkit
